tcdo_pg_tools/250707.crap.fasta
tcdo_pg_tools/__init__.py
tcdo_pg_tools/cli.py
tcdo_pg_tools/coverage_calculator.py
tcdo_pg_tools/fusion_merge.py
tcdo_pg_tools/merge_proteome.py
tcdo_pg_tools/philosopher.crap-gpmdb.fas
tcdo_pg_tools-0.1.0.dist-info/licenses/AUTHORS.rst
tcdo_pg_tools-0.1.0.dist-info/licenses/LICENSE
tcdo_pg_tools-0.1.0.dist-info/METADATA
tcdo_pg_tools-0.1.0.dist-info/WHEEL
tcdo_pg_tools-0.1.0.dist-info/entry_points.txt
tcdo_pg_tools-0.1.0.dist-info/top_level.txt
tcdo_pg_tools-0.1.0.dist-info/RECORD
